{"cameraMode":{"drawMode":0,"name":"Shaded","section":"Shading Mode"},"sceneLighting":true,"audioPlay":false,"sceneViewState":{"showFog":true,"showMaterialUpdate":false,"showSkybox":true,"showFlares":true,"showImageEffects":true,"showParticleSystems":true},"in2DMode":false,"pivot":{"x":-24.814830780029298,"y":-14.536373138427735,"z":-26.6899471282959},"rotation":{"x":-0.0778605043888092,"y":0.9074029922485352,"z":-0.19369997084140778,"w":-0.3647443652153015},"size":23.717151641845704,"orthographic":false}